MANIFEST.in
README.md
setup.cfg
setup.py
discrete_soft_actor_critic/SSM_1.pt
discrete_soft_actor_critic/__init__.py
discrete_soft_actor_critic/classifier_model.pt
discrete_soft_actor_critic/format_obs.py
discrete_soft_actor_critic/network.py
discrete_soft_actor_critic/policy.py
discrete_soft_actor_critic/wrappers.py
smarts_agent_dsac.egg-info/PKG-INFO
smarts_agent_dsac.egg-info/SOURCES.txt
smarts_agent_dsac.egg-info/dependency_links.txt
smarts_agent_dsac.egg-info/requires.txt
smarts_agent_dsac.egg-info/top_level.txt
smarts_agent_dsac.egg-info/zip-safe